NWSh
