Metadata-Version: 2.1
Name: NWSh
Version: 0.1.2
Summary: A little library for the NWSh development
Home-page: https://www.nwsoft.tk
Author: ZCG-Coder
Author-email: andy@nwsoft.tk
License: GPL
